llm_hyperparameters/__init__.py
llm_hyperparameters/tests/__init__.py
llm_hyperparameters/tests/test_track_execution.py
llm_hyperparameters/tests/test_track_hyperparameters.py
llm_hyperparameters/track_execution.py
llm_hyperparameters/track_hyperparameters.py
llm_hyperparameters/utils/__init__.py
llm_hyperparameters/utils/callable_wrapper.py
llm_hyperparameters/utils/tests/__init__.py
llm_hyperparameters/utils/tests/test_callable_wrapper.py
llm_strategy/__init__.py
llm_strategy/adapters.py
llm_strategy/cached_chat_model.py
llm_strategy/chat_chain.py
llm_strategy/llm_function.py
llm_strategy/llm_strategy.py
llm_strategy/testing/__init__.py
llm_strategy/testing/fake_chat_model.py
llm_strategy/testing/fake_llm.py
llm_strategy/testing/tests/test_fake_chat_model.py
llm_strategy/testing/tests/test_fake_llm.py
llm_strategy/tests/manual_text_json_response_format.py
llm_strategy/tests/test_adapters.py
llm_strategy/tests/test_llm_function.py
llm_strategy/tests/test_llm_strategy.py
llm_strategy-2.2.0.dist-info/LICENSE
llm_strategy-2.2.0.dist-info/METADATA
llm_strategy-2.2.0.dist-info/WHEEL
llm_strategy-2.2.0.dist-info/RECORD
