Metadata-Version: 2.1
Name: llm_strategy
Version: 2.2.0
Summary: Directly Connecting Python to LLMs - Dataclasses & Interfaces <-> LLMs
Home-page: https://github.com/blackhc/llm-strategy
Author: Andreas Kirsch, Daedalus Lab Ltd
Author-email: blackhc@gmail.com
Requires-Python: >=3.11,<4.0
Classifier: Programming Language :: Python :: 3
Classifier: Programming Language :: Python :: 3.11
Classifier: Programming Language :: Python :: 3.12
Requires-Dist: langchain (>=0.0.352)
Requires-Dist: langchain-core (>=0,<1)
Requires-Dist: llmtracer (>=1.2.1,<2.0.0)
Requires-Dist: openai (>=1.6.1)
Requires-Dist: pydantic (>=1.10.13,<2.0.0)
Requires-Dist: typing-extensions (>=4.9.0,<5.0.0)
Project-URL: Documentation, https://blackhc.github.io/llm-strategy/
Project-URL: Repository, https://github.com/blackhc/llm-strategy
